torify.py
pyTorify-1.0.dist-info/DESCRIPTION.rst
pyTorify-1.0.dist-info/METADATA
pyTorify-1.0.dist-info/RECORD
pyTorify-1.0.dist-info/WHEEL
pyTorify-1.0.dist-info/metadata.json
pyTorify-1.0.dist-info/top_level.txt
