Metadata-Version: 1.1
Name: pyTorify
Version: 1.0
Summary: Torify python scripts
Home-page: https://github.com/nlitsme/pytorify/
Author: Willem Hengeveld
Author-email: itsme@xs4all.nl
License: MIT
Keywords: TOR networking
Platform: UNKNOWN
Classifier: Development Status :: 4 - Beta
Classifier: Environment :: Console
Classifier: Environment :: Web Environment
Classifier: Intended Audience :: End Users/Desktop
Classifier: Intended Audience :: Developers
Classifier: Intended Audience :: System Administrators
Classifier: License :: OSI Approved :: Python Software Foundation License
Classifier: License :: OSI Approved :: MIT License
Classifier: Operating System :: MacOS :: MacOS X
Classifier: Operating System :: Microsoft :: Windows
Classifier: Operating System :: POSIX
Classifier: Programming Language :: Python :: 2.7
Classifier: Programming Language :: Python :: 3.5
Classifier: Topic :: Internet :: Proxy Servers
